AUTHORS.rst
CONTRIBUTING.rst
HISTORY.rst
LICENSE
MANIFEST.in
README.rst
setup.cfg
setup.py
docs/Makefile
docs/authors.rst
docs/conf.py
docs/contributing.rst
docs/history.rst
docs/index.rst
docs/installation.rst
docs/make.bat
docs/readme.rst
docs/usage.rst
romannumeral/__init__.py
romannumeral/error.py
romannumeral/romannumeral.py
romannumeral.egg-info/PKG-INFO
romannumeral.egg-info/SOURCES.txt
romannumeral.egg-info/dependency_links.txt
romannumeral.egg-info/not-zip-safe
romannumeral.egg-info/top_level.txt
tests/__init__.py
tests/test_romannumeral.py