Metadata-Version: 1.1
Name: romannumeral
Version: 0.2.1
Summary: This package has a class for working with Roman Numerals.
Home-page: https://github.com/jay3686/romannumeral
Author: Jay Patel
Author-email: jay3686@gmail.com
License: BSD
Keywords: romannumeral
Platform: UNKNOWN
Classifier: Development Status :: 2 - Pre-Alpha
Classifier: Intended Audience :: Developers
Classifier: License :: OSI Approved :: BSD License
Classifier: Natural Language :: English
Classifier: Programming Language :: Python :: 2
Classifier: Programming Language :: Python :: 2.6
Classifier: Programming Language :: Python :: 2.7
Classifier: Programming Language :: Python :: 3
Classifier: Programming Language :: Python :: 3.3
Classifier: Programming Language :: Python :: 3.4
